<?xml version="1.0" encoding="UTF-8"?>
<beans xmlns="http://www.springframework.org/schema/beans"
	xmlns:xsi="http://www.w3.org/2001/XMLSchema-instance"
	xsi:schemaLocation="http://www.springframework.org/schema/beans http://www.springframework.org/schema/beans/spring-beans.xsd">
<!-- 

*****************************
Scheduler system for OLAT   *
*****************************
You can either create simple jobs which are executed like every minute or hour or jobs
which are configured with cron style syntax.

If you would like to expose your beans to the Jconsole for accessing your properties add them
to the MBeanExporter Bean at the end.

How to add a new job:
1. Create you class which extends from QuartzJobBean see ChangePresenceJob as example
2. Create a file called "olatextconfig.xml" with your own beans and place it in the same directory as this file. It will be loaded automatically.
3. Add a bean definition where your job is created like ="<bean id="changePresenceJob" class="org.springframework.scheduling.quartz.JobDetailFactoryBean">"
4. Create a scheduler for your definded bean: Either an SimpleTriggerFactoryBean or an CronTriggerFactoryBean
5. Add your trigger bean to the SchedulerFactoryBean list.
-->


<!-- this tells spring to create the quartz scheduler -->
<bean id="schedulerFactoryBean" class="org.springframework.scheduling.quartz.SchedulerFactoryBean" depends-on="database">
	<property name="waitForJobsToCompleteOnShutdown" value="true" />
	<property name="quartzProperties">
		<props>
			<prop key="org.quartz.threadPool.threadCount">5</prop>
			<prop key="org.quartz.scheduler.skipUpdateCheck">true</prop>
			<prop key="org.quartz.scheduler.interruptJobsOnShutdownWithWait">true</prop>
		</props>
	</property>
	<property name="triggers">
        <list>
        	<!-- Include every bean here that should be scheduled -->
            <ref bean="sendNotificationsEmailTrigger" />
            <ref bean="updateStatisticsTrigger"/>
            <ref bean="searchIndexingTrigger"/>
            <ref bean="restTokenTrigger" />
            <ref bean="taskExecutorTrigger" />
            <ref bean="procSamplerTrigger"/>
            <ref bean="systemSamplerTrigger"/>
            <ref bean="acReservationCleanupJob"/>
            <ref bean="mapperSlayerTrigger"/>
            <ref bean="assessmentEvaluateStartOverTrigger"/>
            <ref bean="assessmentNotificationsTrigger"/>
            <ref bean="reminderTrigger"/>
            <ref bean="videoTranscodingTrigger"/>
            <ref bean="automaticLifecycleTrigger"/>
            <ref bean="calendarImportTrigger"/>
            <ref bean="autoCloseLecturesTrigger"/>
            <ref bean="reminderLecturesTrigger"/>
            <ref bean="qualityTrigger"/>
            <ref bean="deleteUserDataExportTrigger"/>
            <ref bean="cspCleanupJob"/>
            <ref bean="adobeCleanupTrigger"/>
            <ref bean="gradingRemindersTrigger"/>
            <ref bean="lifecycleUserTrigger"/>
            <ref bean="fileDeleteUserTrigger"/>
            <ref bean="contactTracingTrigger"/>
            <ref bean="recordingSyncTrigger"/>
            <ref bean="documentAccessDeletionTrigger"/>
        </list>
    </property>
</bean>

<!-- add referenced schedulers here -->

<!-- Example bean for cron style scheduling--> 
<!-- OLAT-5093 start delay ensures there's no conflict with server startup and db not being ready yet -->
<!--
<bean id="cronTrigger" class="org.springframework.scheduling.quartz.CronTriggerFactoryBean">
    <property name="jobDetail" ref="exampleJob" />
    <property name="cronExpression" value="0 0 6 * * ?" />
    <property name="startDelay" value="300000" />
</bean>
 -->

	<!-- SEARCH INDEXING CONFIGURATION -->

	<bean id="searchIndexingTrigger" class="org.springframework.scheduling.quartz.CronTriggerFactoryBean">
	    <property name="jobDetail" ref="org.olat.search.job.${search.indexing.cronjob}" />
	    <property name="cronExpression" ref="searchIndexCronGenerator" />
		<!-- OLAT-5093 start delay ensures there's no conflict with server startup and db not being ready yet -->
	    <property name="startDelay" value="300000" />
	</bean>
	
	<bean id="searchIndexCronGenerator" class="org.olat.search.service.indexer.IndexCronGenerator">
		<property name="tomcatId" value="${tomcat.id}" />
		<property name="enabled" value="${search.indexing.cronjob}" />
		<property name="cronExpression" value="${search.indexing.cronjob.expression}" />
	</bean>
	
	<bean id="org.olat.search.job.enabled" class="org.springframework.scheduling.quartz.JobDetailFactoryBean" lazy-init="true">
	  <property name="jobClass" value="org.olat.search.service.indexer.SearchIndexingJob"/>
	</bean>
	
	<!-- dummy bean -->
	<bean id="org.olat.search.job.disabled" class="org.springframework.scheduling.quartz.JobDetailFactoryBean"  lazy-init="true">
		<!-- NOTE: reusing the notifications.DummyJob here -->
		<property name="jobClass" value="org.olat.core.commons.services.scheduler.DummyJob" />
	</bean>

</beans>
